tmj.py
tmj-1.0.1.dist-info/LICENSE
tmj-1.0.1.dist-info/METADATA
tmj-1.0.1.dist-info/WHEEL
tmj-1.0.1.dist-info/entry_points.txt
tmj-1.0.1.dist-info/top_level.txt
tmj-1.0.1.dist-info/RECORD
