Metadata-Version: 2.1
Name: tmj
Version: 1.0.1
Summary: Small CLI utility script to help me with TMJ disorder isometric jaw exercises.
Home-page: https://github.com/Figglewatts/tmj
Author: Figglewatts
License: UNKNOWN
Keywords: tmj temporomandibular joint disorder
Platform: UNKNOWN
Classifier: Development Status :: 5 - Production/Stable
Classifier: Environment :: Console
Classifier: License :: OSI Approved :: MIT License
Classifier: Operating System :: OS Independent
Classifier: Programming Language :: Python :: 3.7
Classifier: Topic :: Utilities
Classifier: Typing :: Typed
Requires-Python: >=3.7
Requires-Dist: colorama (>=0.4.3)
